LICENSE
MANIFEST.in
README.md
setup.py
the_cannon.egg-info/PKG-INFO
the_cannon.egg-info/SOURCES.txt
the_cannon.egg-info/dependency_links.txt
the_cannon.egg-info/entry_points.txt
the_cannon.egg-info/requires.txt
the_cannon.egg-info/top_level.txt
thecannon/__init__.py
thecannon/__main__.py
thecannon/censoring.py
thecannon/continuum.py
thecannon/fitting.py
thecannon/model.py
thecannon/utils.py
thecannon/tests/__init__.py
thecannon/tests/test_utils.py
thecannon/vectorizer/__init__.py
thecannon/vectorizer/base.py
thecannon/vectorizer/polynomial.py