Metadata-Version: 1.1
Name: the-cannon
Version: 0.2.6
Summary: A data-driven approach to stellar spectroscopy
Home-page: http://thecannon.io
Author: Andrew R. Casey, David W. Hogg, Melissa Ness
Author-email: andrew.casey@monash.edu
License: MIT
Keywords: The Cannon
Platform: UNKNOWN
Classifier: Intended Audience :: Science/Research
Classifier: License :: OSI Approved :: MIT License
Classifier: Operating System :: OS Independent
Classifier: Programming Language :: Python :: 2.7
Classifier: Programming Language :: Python :: 3.6
Classifier: Topic :: Scientific/Engineering :: Astronomy
Classifier: Topic :: Scientific/Engineering :: Physics
